setup.py
pytwig/__init__.py
pytwig/bw_atom.py
pytwig/bw_clip.py
pytwig/bw_device.py
pytwig/bw_file.py
pytwig/bw_object.py
pytwig/bw_panel.py
pytwig/bw_preset.py
pytwig/bw_track.py
pytwig/color.py
pytwig/route.py
pytwig.egg-info/PKG-INFO
pytwig.egg-info/SOURCES.txt
pytwig.egg-info/dependency_links.txt
pytwig.egg-info/not-zip-safe
pytwig.egg-info/top_level.txt