Metadata-Version: 1.0
Name: pytwig
Version: 0.2.1
Summary: Library for modifying and creating Bitwig files. (Not affiliated with Bitwig at all. Something something trademark of Bitwig GmbH etc.)
Home-page: https://gitlab.com/jaxter184/pytwig
Author: jaxter184
Author-email: jaxter184@gmail.com
License: MIT
Keywords: Bitwig music
Platform: UNKNOWN
